{"lastUsed":1611291358884,"path":"C:\/MyStudy\/60_web","projectCount":4,"recentFiles":[{"path":"\/01_Servlet\/src\/com\/mystudy\/servlet","parentWorkspace":"C:\/MyStudy\/60_web","name":"Ex04.java","lastModified":1611194682393},{"path":"\/HANA\/src\/back_","parentWorkspace":"C:\/MyStudy\/60_web","name":"if_1330.java","lastModified":1611288388868,"locationURI":"file:\/C:\/MyStudy\/60_web\/HANA\/src\/back_\/if_1330.java"},{"path":"\/02_JSP\/WebContent","parentWorkspace":"C:\/MyStudy\/60_web","name":"ex10_resp_redirect2.jsp","lastModified":1611284127010,"locationURI":"file:\/C:\/MyStudy\/60_web\/02_JSP\/WebContent\/ex10_resp_redirect2.jsp"},{"path":"\/01_Servlet\/src\/com\/mystudy\/servlet","parentWorkspace":"C:\/MyStudy\/60_web","name":"Ex02.java","lastModified":1611188455084},{"path":"\/01_Servlet\/WebContent","parentWorkspace":"C:\/MyStudy\/60_web","name":"welcome.html","lastModified":1611188455201},{"path":"\/02_JSP\/WebContent","parentWorkspace":"C:\/MyStudy\/60_web","name":"ex09_req.jsp","lastModified":1611281184767,"locationURI":"file:\/C:\/MyStudy\/60_web\/02_JSP\/WebContent\/ex09_req.jsp"},{"path":"\/01_Servlet\/WebContent\/WEB-INF","parentWorkspace":"C:\/MyStudy\/60_web","name":"web.xml","lastModified":1611133080558},{"path":"\/02_JSP\/WebContent\/WEB-INF","parentWorkspace":"C:\/MyStudy\/60_web","name":"실습01.jsp","lastModified":1611277302768,"locationURI":"file:\/C:\/MyStudy\/60_web\/02_JSP\/WebContent\/WEB-INF\/실습01.jsp"},{"path":"\/02_JSP\/WebContent","parentWorkspace":"C:\/MyStudy\/60_web","name":"ex04_resp.jsp","lastModified":1611215748079,"locationURI":"file:\/C:\/MyStudy\/60_web\/02_JSP\/WebContent\/ex04_resp.jsp"},{"path":"\/02_JSP\/WebContent","parentWorkspace":"C:\/MyStudy\/60_web","name":"ex06_declaration_전역변수공유jsp.jsp","lastModified":1611218571694,"locationURI":"file:\/C:\/MyStudy\/60_web\/02_JSP\/WebContent\/ex06_declaration_전역변수공유jsp.jsp"},{"path":"\/01_Servlet\/WebContent","parentWorkspace":"C:\/MyStudy\/60_web","name":"ex06_request.jsp","lastModified":1611205260706},{"path":"\/03_scope\/WebContent","parentWorkspace":"C:\/MyStudy\/60_web","name":"ex01_session.jsp","lastModified":1611291361910,"locationURI":"file:\/C:\/MyStudy\/60_web\/03_scope\/WebContent\/ex01_session.jsp"},{"path":"\/02_JSP\/WebContent","parentWorkspace":"C:\/MyStudy\/60_web","name":"ex09_resp_redirect.jsp","lastModified":1611281448891,"locationURI":"file:\/C:\/MyStudy\/60_web\/02_JSP\/WebContent\/ex09_resp_redirect.jsp"},{"path":"\/01_Servlet\/src\/com\/mystudy\/servlet","parentWorkspace":"C:\/MyStudy\/60_web","name":"Ex01_Hello.java","lastModified":1611127633947},{"path":"\/01_Servlet\/WebContent","parentWorkspace":"C:\/MyStudy\/60_web","name":"ex06_response.jsp","lastModified":1611205246754},{"path":"\/02_JSP\/WebContent","parentWorkspace":"C:\/MyStudy\/60_web","name":"ex10_resp_redirect.jsp","lastModified":1611288433112,"locationURI":"file:\/C:\/MyStudy\/60_web\/02_JSP\/WebContent\/ex10_resp_redirect.jsp"},{"path":"\/01_Servlet\/src\/com\/mystudy\/servlet","parentWorkspace":"C:\/MyStudy\/60_web","name":"Ex03.java","lastModified":1611190760817},{"path":"\/02_JSP\/WebContent","parentWorkspace":"C:\/MyStudy\/60_web","name":"ex10_resp_forward2.jsp","lastModified":1611282646302,"locationURI":"file:\/C:\/MyStudy\/60_web\/02_JSP\/WebContent\/ex10_resp_forward2.jsp"},{"path":"\/02_JSP\/WebContent\/WEB-INF","parentWorkspace":"C:\/MyStudy\/60_web","name":"ex10_req.jsp","lastModified":1611282720170,"locationURI":"file:\/C:\/MyStudy\/60_web\/02_JSP\/WebContent\/WEB-INF\/ex10_req.jsp"},{"path":"\/02_JSP\/WebContent","parentWorkspace":"C:\/MyStudy\/60_web","name":"ex02_scriptlet_sum.jsp","lastModified":1611213922864,"locationURI":"file:\/C:\/MyStudy\/60_web\/02_JSP\/WebContent\/ex02_scriptlet_sum.jsp"},{"path":"\/02_JSP\/WebContent","parentWorkspace":"C:\/MyStudy\/60_web","name":"ex04_req_id_pw.jsp","lastModified":1611217615507,"locationURI":"file:\/C:\/MyStudy\/60_web\/02_JSP\/WebContent\/ex04_req_id_pw.jsp"},{"path":"\/02_JSP\/WebContent","parentWorkspace":"C:\/MyStudy\/60_web","name":"ex07_resp.jsp","lastModified":1611288993435,"locationURI":"file:\/C:\/MyStudy\/60_web\/02_JSP\/WebContent\/ex07_resp.jsp"},{"path":"\/02_JSP\/WebContent","parentWorkspace":"C:\/MyStudy\/60_web","name":"ex08_redirect_forward.jsp","lastModified":1611280765184,"locationURI":"file:\/C:\/MyStudy\/60_web\/02_JSP\/WebContent\/ex08_redirect_forward.jsp"},{"path":"\/02_JSP\/WebContent","parentWorkspace":"C:\/MyStudy\/60_web","name":"ex05_declaration.jsp","lastModified":1611218063043,"locationURI":"file:\/C:\/MyStudy\/60_web\/02_JSP\/WebContent\/ex05_declaration.jsp"},{"path":"\/02_JSP\/WebContent","parentWorkspace":"C:\/MyStudy\/60_web","name":"ex03_expression.jsp","lastModified":1611214793085,"locationURI":"file:\/C:\/MyStudy\/60_web\/02_JSP\/WebContent\/ex03_expression.jsp"},{"path":"\/01_Servlet\/WebContent","parentWorkspace":"C:\/MyStudy\/60_web","name":"ex05.html","lastModified":1611202940465},{"path":"\/01_Servlet\/WebContent\/WEB-INF","parentWorkspace":"C:\/MyStudy\/60_web","name":"jspEx.jsp","lastModified":1611188455023},{"path":"\/01_Servlet\/src\/com\/mystudy\/servlet","parentWorkspace":"C:\/MyStudy\/60_web","name":"TestFormat.java","lastModified":1611202761128},{"path":"\/01_Servlet\/WebContent","parentWorkspace":"C:\/MyStudy\/60_web","name":"ex04.html","lastModified":1611194849765},{"path":"\/01_Servlet\/WebContent","parentWorkspace":"C:\/MyStudy\/60_web","name":"ex03.html","lastModified":1611139112438},{"path":"\/02_JSP\/WebContent","parentWorkspace":"C:\/MyStudy\/60_web","name":"ex01_scriptlet.jsp","lastModified":1611210353862,"locationURI":"file:\/C:\/MyStudy\/60_web\/02_JSP\/WebContent\/ex01_scriptlet.jsp"},{"path":"\/02_JSP\/WebContent","parentWorkspace":"C:\/MyStudy\/60_web","name":"ex07_req_coffee.jsp","lastModified":1611277341247,"locationURI":"file:\/C:\/MyStudy\/60_web\/02_JSP\/WebContent\/ex07_req_coffee.jsp"},{"path":"\/02_JSP\/WebContent","parentWorkspace":"C:\/MyStudy\/60_web","name":"ex10_resp_forward.jsp","lastModified":1611282633571,"locationURI":"file:\/C:\/MyStudy\/60_web\/02_JSP\/WebContent\/ex10_resp_forward.jsp"},{"path":"\/01_Servlet\/src\/com\/mystudy\/servlet","parentWorkspace":"C:\/MyStudy\/60_web","name":"Ex05.java","lastModified":1611203548067}]}